xampy/__init__.py
xampy/xampy.py
XamPy-0.1.4.2.dist-info/LICENSE
XamPy-0.1.4.2.dist-info/METADATA
XamPy-0.1.4.2.dist-info/WHEEL
XamPy-0.1.4.2.dist-info/top_level.txt
XamPy-0.1.4.2.dist-info/RECORD
