Metadata-Version: 2.1
Name: XamPy
Version: 0.1.4.2
Summary: A Data Science Package written in python.
Home-page: UNKNOWN
Author: Max Paul
Author-email: maxkpaul21@gmail.com
License: UNKNOWN
Platform: UNKNOWN
Classifier: Programming Language :: Python :: 3
Classifier: License :: OSI Approved :: MIT License
Classifier: Operating System :: OS Independent
Requires-Dist: nltk
Requires-Dist: pandas
Requires-Dist: vaderSentiment
Requires-Dist: numpy
Requires-Dist: sklearn
Requires-Dist: textblob
Requires-Dist: datetime
Requires-Dist: matplotlib
